pyckett/__init__.py
pyckett/clitools/__init__.py
pyckett/clitools/addparameters.py
pyckett/clitools/automaticfit.py
pyckett/clitools/duplicates.py
pyckett/clitools/omitparameters.py
pyckett/clitools/partitionfunction.py
pyckett/clitools/pmix.py
pyckett/clitools/report.py
pyckett/clitools/separatefits.py
pyckett/clitools/shortcuts.py
pyckett/clitools/uncertainties.py
pyckett-0.1.29.dist-info/licenses/LICENSE
pyckett-0.1.29.dist-info/METADATA
pyckett-0.1.29.dist-info/WHEEL
pyckett-0.1.29.dist-info/entry_points.txt
pyckett-0.1.29.dist-info/top_level.txt
pyckett-0.1.29.dist-info/RECORD
