Metadata-Version: 2.4
Name: pyckett
Version: 0.1.29
Summary: A wrapper around Pickett's SPFIT and SPCAT
Author-email: Luis Bonah <bonah@ph1.uni-koeln.de>
Project-URL: Homepage, https://github.com/Ltotheois/Pyckett/
Keywords: pickett,spectroscopy,spfit,spcat
Classifier: Programming Language :: Python :: 3
Classifier: License :: OSI Approved :: MIT License
Classifier: Operating System :: OS Independent
Requires-Python: >=3.7
License-File: LICENSE
Requires-Dist: numpy
Requires-Dist: pandas
Requires-Dist: matplotlib
Dynamic: license-file
